uart_ble/__init__.py
uart_ble/ble_utils.py
uart_ble/definitions.py
uart_ble/imu_data.py
uart_ble/live_data.py
uart_ble/sensor_threads.py
uart_ble/uart_utils.py
uart_ble-0.1.7.dist-info/METADATA
uart_ble-0.1.7.dist-info/WHEEL
uart_ble-0.1.7.dist-info/RECORD
